{
  "project_info": {
    "project_number": "165600705820",
    "project_id": "projectv-ee76d",
    "storage_bucket": "projectv-ee76d.firebasestorage.app"
  },
  "client": [
    {
      "client_info": {
        "mobilesdk_app_id": "1:165600705820:android:07b849f9d586f9f97d0ed9",
        "android_client_info": {
          "package_name": "com.sina.projectv"
        }
      },
      "oauth_client": [
        {
          "client_id": "165600705820-cs1a6hsqed20ftbbmseh5umeeqigs3f1.apps.googleusercontent.com",
          "client_type": 1,
          "android_info": {
            "package_name": "com.sina.projectv",
            "certificate_hash": "ab74000a37eab765c55dce6cb82a885b82dde35c"
          }
        },
        {
          "client_id": "165600705820-5c7q78qiv2cg79toaeoi8hebqm8g30h2.apps.googleusercontent.com",
          "client_type": 3
        }
      ],
      "api_key": [
        {
          "current_key": "AIzaSyCwwjH9DYjEz8R-DcniUP0L9TLOe7L4zc4"
        }
      ],
      "services": {
        "appinvite_service": {
          "other_platform_oauth_client": [
            {
              "client_id": "165600705820-5c7q78qiv2cg79toaeoi8hebqm8g30h2.apps.googleusercontent.com",
              "client_type": 3
            }
          ]
        }
      }
    }
  ],
  "configuration_version": "1"
}